eb_evaluation/__init__.py
eb_evaluation/adjustment/__init__.py
eb_evaluation/adjustment/_utils.py
eb_evaluation/adjustment/ral.py
eb_evaluation/dataframe/__init__.py
eb_evaluation/dataframe/entity.py
eb_evaluation/dataframe/group.py
eb_evaluation/dataframe/hierarchy.py
eb_evaluation/dataframe/panel.py
eb_evaluation/dataframe/single.py
eb_evaluation/model_selection/__init__.py
eb_evaluation/model_selection/auto_engine.py
eb_evaluation/model_selection/compare.py
eb_evaluation/model_selection/cwsl_regressor.py
eb_evaluation/model_selection/electric_barometer.py
eb_evaluation/utils/__init__.py
eb_evaluation/utils/validation.py
eb_evaluation-0.2.4.dist-info/licenses/LICENSE
eb_evaluation-0.2.4.dist-info/METADATA
eb_evaluation-0.2.4.dist-info/WHEEL
eb_evaluation-0.2.4.dist-info/top_level.txt
eb_evaluation-0.2.4.dist-info/RECORD
