Metadata-Version: 2.4
Name: eb-evaluation
Version: 0.2.4
Summary: Electric Barometer: DataFrame-based evaluation utilities for CWSL and related metrics.
Author-email: "Kyle Corrie (Economistician)" <kcorrie@economistician.com>
License-Expression: BSD-3-Clause
Project-URL: Homepage, https://github.com/Economistician/eb-evaluation
Project-URL: Repository, https://github.com/Economistician/eb-evaluation
Project-URL: Issues, https://github.com/Economistician/eb-evaluation/issues
Project-URL: Documentation, https://github.com/Economistician/eb-docs
Keywords: electric-barometer,forecast-evaluation,asymmetric-loss,readiness,forecasting,pandas
Classifier: Programming Language :: Python :: 3
Classifier: Programming Language :: Python :: 3 :: Only
Classifier: Programming Language :: Python :: 3.10
Classifier: Programming Language :: Python :: 3.11
Classifier: Programming Language :: Python :: 3.12
Classifier: Programming Language :: Python :: 3.13
Classifier: Operating System :: OS Independent
Requires-Python: >=3.10
License-File: LICENSE
Requires-Dist: numpy>=1.24
Requires-Dist: pandas>=2.0
Requires-Dist: eb-metrics<0.3,>=0.2
Requires-Dist: eb-adapters<0.3,>=0.2
Provides-Extra: test
Requires-Dist: pytest>=8.0; extra == "test"
Requires-Dist: scikit-learn>=1.3; extra == "test"
Provides-Extra: dev
Requires-Dist: pytest>=8.0; extra == "dev"
Requires-Dist: pytest-cov>=5.0; extra == "dev"
Dynamic: license-file
